brazilfiscalreport/__init__.py
brazilfiscalreport/__main__.py
brazilfiscalreport/cli.py
brazilfiscalreport/pdf_element.py
brazilfiscalreport/utils.py
brazilfiscalreport/xfpdf.py
brazilfiscalreport/dacce/__init__.py
brazilfiscalreport/dacce/dacce.py
brazilfiscalreport/dacte/__init__.py
brazilfiscalreport/dacte/config.py
brazilfiscalreport/dacte/dacte.py
brazilfiscalreport/dacte/dacte_conf.py
brazilfiscalreport/dacte/generate_qrcode.py
brazilfiscalreport/damdfe/__init__.py
brazilfiscalreport/damdfe/config.py
brazilfiscalreport/damdfe/damdfe.py
brazilfiscalreport/damdfe/damdfe_conf.py
brazilfiscalreport/danfe/__init__.py
brazilfiscalreport/danfe/config.py
brazilfiscalreport/danfe/danfe.py
brazilfiscalreport/danfe/danfe_basic_field.py
brazilfiscalreport/danfe/danfe_block.py
brazilfiscalreport/danfe/danfe_code.py
brazilfiscalreport/danfe/danfe_conf.py
brazilfiscalreport/danfe/danfe_emit_info.py
brazilfiscalreport/danfe/danfe_ident_info.py
brazilfiscalreport/danfe/danfe_verification_msg.py
brazilfiscalreport/danfe/models.py
brazilfiscalreport-0.5.33.dist-info/licenses/LICENSE
brazilfiscalreport-0.5.33.dist-info/METADATA
brazilfiscalreport-0.5.33.dist-info/WHEEL
brazilfiscalreport-0.5.33.dist-info/entry_points.txt
brazilfiscalreport-0.5.33.dist-info/top_level.txt
brazilfiscalreport-0.5.33.dist-info/RECORD
