Metadata-Version: 2.4
Name: BrazilFiscalReport
Version: 0.5.33
Summary: Python library for generating Brazilian auxiliary fiscal documents in PDF from XML documents.
Author: Engenere
License:   GNU LESSER GENERAL PUBLIC LICENSE
Project-URL: homepage, https://github.com/Engenere/BrazilFiscalReport
Keywords: nfe,danfe,xml,pdf,documento,fiscal,auxiliar,converter,generator,cce,dacce
Classifier: Development Status :: 4 - Beta
Classifier: Intended Audience :: Developers
Classifier: License :: OSI Approved :: GNU Affero General Public License v3
Classifier: Operating System :: OS Independent
Classifier: Programming Language :: Python
Classifier: Programming Language :: Python :: 3
Classifier: Programming Language :: Python :: 3 :: Only
Classifier: Programming Language :: Python :: 3.8
Classifier: Programming Language :: Python :: 3.9
Classifier: Programming Language :: Python :: 3.10
Classifier: Programming Language :: Python :: 3.11
Classifier: Programming Language :: Python :: 3.12
Classifier: Programming Language :: Python :: 3.13
Classifier: Topic :: Software Development :: Libraries :: Python Modules
Requires-Python: >=3.8
License-File: LICENSE
Requires-Dist: fpdf2>=2.8.3
Requires-Dist: phonenumbers
Requires-Dist: python-barcode
Provides-Extra: dacte
Requires-Dist: qrcode; extra == "dacte"
Provides-Extra: damdfe
Requires-Dist: qrcode; extra == "damdfe"
Provides-Extra: cli
Requires-Dist: click; extra == "cli"
Requires-Dist: PyYAML; extra == "cli"
Dynamic: license-file
